pystreasy/__init__.py
pystreasy/utils.py
pystreasy-0.1.4.dist-info/LICENSE.md
pystreasy-0.1.4.dist-info/METADATA
pystreasy-0.1.4.dist-info/WHEEL
pystreasy-0.1.4.dist-info/RECORD
